grgrlib/__init__.py
grgrlib/__version__.py
grgrlib/datatools.py
grgrlib/dist.py
grgrlib/econtools.py
grgrlib/generic.py
grgrlib/h5.py
grgrlib/hanktools.py
grgrlib/jaxed.py
grgrlib/legacy.py
grgrlib/linalg.py
grgrlib/multiprocessing.py
grgrlib/njitted.py
grgrlib/numerics.py
grgrlib/optimize.py
grgrlib/plots.py
grgrlib/stats.py
grgrlib-0.2.1.dist-info/LICENSE
grgrlib-0.2.1.dist-info/METADATA
grgrlib-0.2.1.dist-info/WHEEL
grgrlib-0.2.1.dist-info/top_level.txt
grgrlib-0.2.1.dist-info/RECORD
