Metadata-Version: 2.1
Name: grgrlib
Version: 0.2.1
Summary: Various insanely helpful functions
Home-page: https://github.com/gboehl/grgrlib
Author: Gregor Boehl
Author-email: admin@gregorboehl.com
License: MIT
Classifier: License :: OSI Approved :: MIT License
Classifier: Programming Language :: Python :: 3
Classifier: Programming Language :: Python :: 3.9
License-File: LICENSE
Requires-Dist: numpy
Requires-Dist: scipy
Requires-Dist: matplotlib
Provides-Extra: data
Requires-Dist: pandas ; extra == 'data'
Provides-Extra: jaxed
Requires-Dist: jax ; extra == 'jaxed'
Requires-Dist: jaxlib ; extra == 'jaxed'
Provides-Extra: njitted
Requires-Dist: numba ; extra == 'njitted'
Provides-Extra: opti
Requires-Dist: chaospy ; extra == 'opti'
